bibliotecaTest/__init__.py
bibliotecaTest/helloTest.py
hello_worldVictorAugusto-0.0.1.dist-info/LICENCE
hello_worldVictorAugusto-0.0.1.dist-info/METADATA
hello_worldVictorAugusto-0.0.1.dist-info/WHEEL
hello_worldVictorAugusto-0.0.1.dist-info/top_level.txt
hello_worldVictorAugusto-0.0.1.dist-info/RECORD
