Metadata-Version: 2.1
Name: hello-worldVictorAugusto
Version: 0.0.1
Summary: Uma biblioteca simples que exibe Hello, World!
Author: Victor Augusto
Author-email: victoraugustodocarmo32@gmail.com
License: MIT License
Keywords: hello world
License-File: LICENCE
